intellinet_pdu_ctrl/__init__.py
intellinet_pdu_ctrl/api.py
intellinet_pdu_ctrl/py.typed
intellinet_pdu_ctrl/types.py
intellinet_pdu_ctrl/udp.py
intellinet_pdu_ctrl/utils.py
intellinet_pdu_ctrl-0.8.3.dist-info/LICENSE
intellinet_pdu_ctrl-0.8.3.dist-info/METADATA
intellinet_pdu_ctrl-0.8.3.dist-info/WHEEL
intellinet_pdu_ctrl-0.8.3.dist-info/entry_points.txt
intellinet_pdu_ctrl-0.8.3.dist-info/RECORD
