Metadata-Version: 2.3
Name: intellinet-pdu-ctrl
Version: 0.8.3
Summary: asyncio client library for intellinet pdus
License: MIT
Author: Josh Gruenstein
Author-email: josh@tutorintelligence.com
Requires-Python: >=3.10,<4.0
Classifier: License :: OSI Approved :: MIT License
Classifier: Programming Language :: Python :: 3
Classifier: Programming Language :: Python :: 3.10
Classifier: Programming Language :: Python :: 3.11
Classifier: Programming Language :: Python :: 3.12
Classifier: Programming Language :: Python :: 3.13
Requires-Dist: aiohttp (>=3.8.5,<4.0.0)
Requires-Dist: lxml (>=5.3.0,<6.0.0)
Requires-Dist: typing-extensions (>=4.11.0,<5.0.0)
